StringQuartet/StringQuartet.py
StringQuartet/__init__.py
StringQuartet-1.1.1.dist-info/METADATA
StringQuartet-1.1.1.dist-info/WHEEL
StringQuartet-1.1.1.dist-info/top_level.txt
StringQuartet-1.1.1.dist-info/RECORD
