Metadata-Version: 2.1
Name: StringQuartet
Version: 1.1.1
Summary: Class to mark and manipulate parts of a string that match a regex
Home-page: UNKNOWN
Author: Alan Bacon
Author-email: alan@bacontowers.co.uk
License: UNKNOWN
Platform: UNKNOWN
